pds_benchmark/__init__.py
pds_benchmark/cli.py
pds_benchmark/config.py
pds_benchmark/datagen.py
pds_benchmark/executor.py
pds_benchmark/plugins/__init__.py
pds_benchmark/plugins/duckdb/__init__.py
pds_benchmark/plugins/duckdb/queries/tpcds/q1.py
pds_benchmark/plugins/duckdb/queries/tpcds/q2.py
pds_benchmark/plugins/duckdb/queries/tpch/q1.py
pds_benchmark/plugins/duckdb/queries/tpch/q10.py
pds_benchmark/plugins/duckdb/queries/tpch/q11.py
pds_benchmark/plugins/duckdb/queries/tpch/q12.py
pds_benchmark/plugins/duckdb/queries/tpch/q13.py
pds_benchmark/plugins/duckdb/queries/tpch/q14.py
pds_benchmark/plugins/duckdb/queries/tpch/q15.py
pds_benchmark/plugins/duckdb/queries/tpch/q16.py
pds_benchmark/plugins/duckdb/queries/tpch/q17.py
pds_benchmark/plugins/duckdb/queries/tpch/q18.py
pds_benchmark/plugins/duckdb/queries/tpch/q19.py
pds_benchmark/plugins/duckdb/queries/tpch/q2.py
pds_benchmark/plugins/duckdb/queries/tpch/q20.py
pds_benchmark/plugins/duckdb/queries/tpch/q21.py
pds_benchmark/plugins/duckdb/queries/tpch/q22.py
pds_benchmark/plugins/duckdb/queries/tpch/q3.py
pds_benchmark/plugins/duckdb/queries/tpch/q4.py
pds_benchmark/plugins/duckdb/queries/tpch/q5.py
pds_benchmark/plugins/duckdb/queries/tpch/q6.py
pds_benchmark/plugins/duckdb/queries/tpch/q7.py
pds_benchmark/plugins/duckdb/queries/tpch/q8.py
pds_benchmark/plugins/duckdb/queries/tpch/q9.py
pds_benchmark/plugins/pandas/__init__.py
pds_benchmark/plugins/polars/__init__.py
pds_benchmark/plugins/polars/queries/tpcds/q1.py
pds_benchmark/plugins/polars/queries/tpcds/q10.py
pds_benchmark/plugins/polars/queries/tpcds/q2.py
pds_benchmark/plugins/polars/queries/tpcds/q3.py
pds_benchmark/plugins/polars/queries/tpcds/q4.py
pds_benchmark/plugins/polars/queries/tpcds/q5.py
pds_benchmark/plugins/polars/queries/tpcds/q6.py
pds_benchmark/plugins/polars/queries/tpcds/q7.py
pds_benchmark/plugins/polars/queries/tpcds/q8.py
pds_benchmark/plugins/polars/queries/tpcds/q9.py
pds_benchmark/plugins/polars/queries/tpch/q1.py
pds_benchmark-0.1.0.dist-info/METADATA
pds_benchmark-0.1.0.dist-info/WHEEL
pds_benchmark-0.1.0.dist-info/entry_points.txt
pds_benchmark-0.1.0.dist-info/RECORD
