Metadata-Version: 2.4
Name: pds-benchmark
Version: 0.1.0
Summary: A minimal, Polars-focused data processing benchmark suite
Project-URL: Homepage, https://github.com/pds-benchmark/pds-benchmark
Project-URL: Repository, https://github.com/pds-benchmark/pds-benchmark
Project-URL: Issues, https://github.com/pds-benchmark/pds-benchmark/issues
Author: PDS Benchmark Contributors
License: MIT
Keywords: benchmark,data-processing,performance,polars,tpc-h
Classifier: Development Status :: 4 - Beta
Classifier: Intended Audience :: Developers
Classifier: License :: OSI Approved :: MIT License
Classifier: Programming Language :: Python :: 3
Classifier: Programming Language :: Python :: 3.11
Classifier: Programming Language :: Python :: 3.12
Classifier: Programming Language :: Python :: 3.13
Classifier: Topic :: Software Development :: Testing
Classifier: Topic :: System :: Benchmark
Requires-Python: >=3.11
Requires-Dist: click>=8.0.0
Requires-Dist: duckdb>=1.3.2
Requires-Dist: pandas
Requires-Dist: polars>=1.0.0
Requires-Dist: pyarrow
Requires-Dist: tpchgen-cli>=1.1.1
Requires-Dist: tqdm>=4.0.0
